csvlike/__init__.py
csvlike/__meta__.py
csvlike/csv.py
csvlike/helpers.py
csvlike-1.0.0.dist-info/LICENCE.md
csvlike-1.0.0.dist-info/METADATA
csvlike-1.0.0.dist-info/WHEEL
csvlike-1.0.0.dist-info/entry_points.txt
csvlike-1.0.0.dist-info/top_level.txt
csvlike-1.0.0.dist-info/RECORD
