Metadata-Version: 2.1
Name: csvlike
Version: 1.0.0
Summary: Read CSV-like files
Home-page: https://github.com/MikeSmithEU/csvlike/
Author: MikeSmithEU
Author-email: github@mikesmith.eu
Maintainer: MikeSmithEU
Maintainer-email: github@mikesmith.eu
License: MIT
Platform: any
Classifier: Programming Language :: Python
Classifier: Programming Language :: Python :: 3
Classifier: Programming Language :: Python :: 3.5
Classifier: Programming Language :: Python :: 3.6
Classifier: Programming Language :: Python :: 3.7
Classifier: Programming Language :: Python :: 3.8
Classifier: Programming Language :: Python :: 3.9
Classifier: License :: OSI Approved :: MIT License
Requires-Python: >=3.5
Provides-Extra: docs
Requires-Dist: sphinx (==3.2.1) ; extra == 'docs'
Requires-Dist: sphinx-rtd-theme (==0.4.2) ; extra == 'docs'
Requires-Dist: sphinx-argparse (==0.2.5) ; extra == 'docs'
Requires-Dist: sphinxcontrib-mermaid (==0.4.0) ; extra == 'docs'
Provides-Extra: test
Requires-Dist: pytest (==4.2.0) ; extra == 'test'
Requires-Dist: pycodestyle (==2.5.0) ; extra == 'test'
Requires-Dist: pytest-cov (==2.5.1) ; extra == 'test'
Requires-Dist: attrs (==19.1.0) ; extra == 'test'
